setup.py
server/__init__.py
server/server.py
server/common/__init__.py
server/common/decos.py
server/common/descryptors.py
server/common/errors.py
server/common/metaclasses.py
server/common/utils.py
server/common/variables.py
server/logs/__init__.py
server/logs/config_client_log.py
server/logs/config_server_log.py
server/server/__init__.py
server/server/add_user.py
server/server/config_window.py
server/server/core.py
server/server/database.py
server/server/main_window.py
server/server/remove_user.py
server/server/stat_window.py
server/unit_tests/__init__.py
server_chat_pyqt_march.egg-info/PKG-INFO
server_chat_pyqt_march.egg-info/SOURCES.txt
server_chat_pyqt_march.egg-info/dependency_links.txt
server_chat_pyqt_march.egg-info/top_level.txt